HYOTC/Equity/American.py
HYOTC/Equity/BSM.py
HYOTC/FDM/SD1_FDM.py
HYOTC/FICC/IR.py
HYOTC/MC/SD1.py
hyotc-0.1.1.dist-info/METADATA
hyotc-0.1.1.dist-info/WHEEL
hyotc-0.1.1.dist-info/top_level.txt
hyotc-0.1.1.dist-info/RECORD
