Metadata-Version: 2.4
Name: HYOTC
Version: 0.1.1
Summary: Derivatives for HanYang Securties
Author-email: HST <ye0077@naver.com>
Classifier: Programming Language :: Python :: 3
Classifier: License :: OSI Approved :: MIT License
Classifier: Operating System :: OS Independent
Requires-Python: >=3.8
